nico/Annotations.py
nico/Covariations.py
nico/Interactions.py
nico/__init__.py
nico/utils/SCTransform.py
nico/utils/__init__.py
nico/utils/pyliger_utilities.py
nico_gruenlab-1.3.0.dist-info/LICENSE
nico_gruenlab-1.3.0.dist-info/METADATA
nico_gruenlab-1.3.0.dist-info/WHEEL
nico_gruenlab-1.3.0.dist-info/top_level.txt
nico_gruenlab-1.3.0.dist-info/RECORD
