Metadata-Version: 2.2
Name: nico-gruenlab
Version: 1.3.0
Summary: This package finds covariation patterns between interacted niche cell types from single-cell resolution spatial transcriptomics data.
Author: Christian
Author-email: <xyz@gmail.com>
Keywords: python,tissue niche,niche,spatial transcriptomics,single-cell RNA sequencing,scRNAseq,scRNA-seq,MERFISH,seqFISH,STARmap,nico,niche covariation
Classifier: Development Status :: 1 - Planning
Classifier: Intended Audience :: Developers
Classifier: Programming Language :: Python :: 3.11
Classifier: Operating System :: OS Independent
Classifier: License :: OSI Approved :: MIT License
License-File: LICENSE
Requires-Dist: scanpy==1.9.6
Requires-Dist: seaborn==0.12.2
Requires-Dist: scipy==1.11.3
Requires-Dist: matplotlib==3.7.3
Requires-Dist: numpy==1.26.1
Requires-Dist: networkx==3.2.1
Requires-Dist: gseapy==1.0.6
Requires-Dist: numba==0.58.1
Requires-Dist: xlsxwriter==3.1.9
Requires-Dist: pydot==1.4.2
Requires-Dist: scikit-learn==1.3.2
Requires-Dist: pandas==2.1.1
Requires-Dist: KDEpy==1.1.8
Requires-Dist: pygraphviz==1.11
Requires-Dist: leidenalg
Dynamic: author
Dynamic: author-email
Dynamic: classifier
Dynamic: description
Dynamic: description-content-type
Dynamic: keywords
Dynamic: requires-dist
Dynamic: summary
